[
    {
        "id": 1,
        "title": "Remuneraciones ant 1994",
        "text": "Para las remuneaaiones anteriores a 1994....  "
    },
    {
        "id": 2,
        "title": "Insalubre",
        "text": "El trabajo riesgoso o insalubre es aquel que se realiza en lugares donde las condiciones, la modalidad o la naturaleza del trabajo afectan a la salud. Las personas que hayan trabajado en estas condiciones tienen requisitos diferentes para acceder a la jubilación, según la actividad realizada.        "
    }
]